validatexmls/__init__.py
validatexmls/validatexmls.py
validatexmls-0.1.21.dist-info/DESCRIPTION.rst
validatexmls-0.1.21.dist-info/METADATA
validatexmls-0.1.21.dist-info/RECORD
validatexmls-0.1.21.dist-info/WHEEL
validatexmls-0.1.21.dist-info/entry_points.txt
validatexmls-0.1.21.dist-info/metadata.json
validatexmls-0.1.21.dist-info/top_level.txt
