Metadata-Version: 2.0
Name: validatexmls
Version: 0.1.21
Summary: validatexmls validates an xml against a XSD and put it in the right output directory
Home-page: https://github.com/nielspostma/validatexmls
Author: Niels Postma
Author-email: niels.postma@gmail.com
License: MIT
Keywords: validate xml xsd lxml
Platform: UNKNOWN
Classifier: Development Status :: 3 - Alpha
Classifier: Intended Audience :: Developers
Classifier: License :: OSI Approved :: MIT License
Classifier: Programming Language :: Python :: 3.6
Requires-Dist: lxml
Requires-Dist: click
